{
  "configVersion": 1,
  "timestamp": 1770308086864,
  "index": "/index.html",
  "assetGroups": [
    {
      "name": "app",
      "installMode": "prefetch",
      "updateMode": "prefetch",
      "cacheQueryOptions": {
        "ignoreVary": true
      },
      "urls": [
        "/chunk-23KMSIXT.js",
        "/chunk-2YXPGKP6.js",
        "/chunk-3EGQBMJO.js",
        "/chunk-3FMCGYQ4.js",
        "/chunk-3I4VER4M.js",
        "/chunk-3PX7F27W.js",
        "/chunk-3UEZSA3G.js",
        "/chunk-474YFGF3.js",
        "/chunk-4NSCISVX.js",
        "/chunk-5HDX4MU7.js",
        "/chunk-5MLLNZB4.js",
        "/chunk-5RY525K3.js",
        "/chunk-6BHTYI5B.js",
        "/chunk-6E3KGWLL.js",
        "/chunk-6Q4QUX6Y.js",
        "/chunk-6WEONDX6.js",
        "/chunk-7UZYWCAJ.js",
        "/chunk-ANLIW4M2.js",
        "/chunk-AOZPS5RL.js",
        "/chunk-AS3FNOMA.js",
        "/chunk-B4CAXBEG.js",
        "/chunk-BEFSL7UU.js",
        "/chunk-BYAQRIZS.js",
        "/chunk-C7TNQJZF.js",
        "/chunk-CI3K2WSU.js",
        "/chunk-CKE2KE55.js",
        "/chunk-CQALS4LV.js",
        "/chunk-CV62PXL2.js",
        "/chunk-CVA3OUYK.js",
        "/chunk-D5BJGGEH.js",
        "/chunk-DEKAXLAX.js",
        "/chunk-E7AQ6X4Y.js",
        "/chunk-E7H4FHC6.js",
        "/chunk-EBJYW3C2.js",
        "/chunk-EE2HNWMR.js",
        "/chunk-EE3OZHXG.js",
        "/chunk-EJWNUG5D.js",
        "/chunk-EQDQRRRY.js",
        "/chunk-EWYNZ3T6.js",
        "/chunk-FBCHPQNP.js",
        "/chunk-FJY5KO7T.js",
        "/chunk-FUINNIJL.js",
        "/chunk-FWCPX4QV.js",
        "/chunk-GOSO7CR6.js",
        "/chunk-GVQJJU27.js",
        "/chunk-GWNY4E3S.js",
        "/chunk-HFRGPHGK.js",
        "/chunk-HZBF5Z2J.js",
        "/chunk-IABRCUVS.js",
        "/chunk-IE4XPFBV.js",
        "/chunk-IN5CGMY2.js",
        "/chunk-ISPOGFK5.js",
        "/chunk-J6FMTRGJ.js",
        "/chunk-JBX6OC6U.js",
        "/chunk-JFPH4BJU.js",
        "/chunk-JO4DRFJG.js",
        "/chunk-JRV6D33A.js",
        "/chunk-KSJ6ZHDJ.js",
        "/chunk-KYEGXUPT.js",
        "/chunk-L267FACM.js",
        "/chunk-L64YGAYQ.js",
        "/chunk-LMV7XNWS.js",
        "/chunk-LXBTVQ6C.js",
        "/chunk-LYWS3EQM.js",
        "/chunk-M2VBT7VT.js",
        "/chunk-MXRZJWAE.js",
        "/chunk-NKKODL53.js",
        "/chunk-NQ5JYPMZ.js",
        "/chunk-OCAOS45R.js",
        "/chunk-ODKAJW66.js",
        "/chunk-P5ZGQUYK.js",
        "/chunk-PCDFLCFQ.js",
        "/chunk-PXQKGGUN.js",
        "/chunk-PY62MJCA.js",
        "/chunk-Q6MIBXXU.js",
        "/chunk-QJE73BZP.js",
        "/chunk-QVMFGACW.js",
        "/chunk-R265V6BS.js",
        "/chunk-RHXYTOW7.js",
        "/chunk-SFZAX3ZK.js",
        "/chunk-STMJJCCP.js",
        "/chunk-TAMGTV3V.js",
        "/chunk-TDSKTGHS.js",
        "/chunk-TJHQUM2E.js",
        "/chunk-TQK6WSWP.js",
        "/chunk-U6EES5RG.js",
        "/chunk-UWEQFVWP.js",
        "/chunk-V54ZWV6J.js",
        "/chunk-V6MGZ35S.js",
        "/chunk-VG5Y5GOD.js",
        "/chunk-WR5RRO56.js",
        "/chunk-WZ35W2ON.js",
        "/chunk-X6CIBPON.js",
        "/chunk-XPONP6K5.js",
        "/chunk-Y6TWN2IB.js",
        "/chunk-YGREV7VD.js",
        "/chunk-YHXWWA2F.js",
        "/chunk-YSK4XEVS.js",
        "/chunk-YYATEFRI.js",
        "/chunk-ZNVG5ZVS.js",
        "/chunk-ZQX6GPNJ.js",
        "/chunk-ZX7FFNRS.js",
        "/index.html",
        "/main-EDQZWXBM.js",
        "/polyfills-7UFKQPMO.js",
        "/styles-M7H7SQDV.css"
      ],
      "patterns": []
    },
    {
      "name": "assets",
      "installMode": "lazy",
      "updateMode": "prefetch",
      "cacheQueryOptions": {
        "ignoreVary": true
      },
      "urls": [
        "/media/layers-2x-TBM42ERR.png",
        "/media/layers-55W3Q4RM.png",
        "/media/marker-icon-2V3QKKVC.png"
      ],
      "patterns": []
    }
  ],
  "dataGroups": [],
  "hashTable": {
    "/chunk-23KMSIXT.js": "4b709cbc464217ac0f0a8711424dcec6ee2f956c",
    "/chunk-2YXPGKP6.js": "33ea865ea64c6f3e3158433e28e2679f696264e6",
    "/chunk-3EGQBMJO.js": "7ce705c9d54ac585ee6c6b4f44ae6c48cb82306a",
    "/chunk-3FMCGYQ4.js": "b0e12504262a3d7761ff2482f65c20ea6a330576",
    "/chunk-3I4VER4M.js": "c48fabf02791b8b215bd8e5ea3d62c01d44af8cc",
    "/chunk-3PX7F27W.js": "62782a463f29c6b99f25b92982eb93cce77fb5d9",
    "/chunk-3UEZSA3G.js": "60cd05a841b7a6771d37be99699e858bef8745d5",
    "/chunk-474YFGF3.js": "136c05c19845921ffc633bf954e9285aca52f0a6",
    "/chunk-4NSCISVX.js": "afb1e16e5c33f828c9601925cad624e485b04456",
    "/chunk-5HDX4MU7.js": "ea5e98d9e8aea03b912af90dd65065d3d722efc8",
    "/chunk-5MLLNZB4.js": "0ebbae64df7d84612f8c25cc0e094920a2e71a9f",
    "/chunk-5RY525K3.js": "dc123e4de53ce74fef4c8b75ad2b6519916648d8",
    "/chunk-6BHTYI5B.js": "e247613fd221ee5005dc4438d4fb12734bfbdbab",
    "/chunk-6E3KGWLL.js": "429f5ef99a3ebcc6bd192aa8993802900751755c",
    "/chunk-6Q4QUX6Y.js": "3e1c59e1ac7a0ff91ad0b24badd7c698bb32bdf4",
    "/chunk-6WEONDX6.js": "58b34a7b5563f5d7ddef58fb81d982846e7a3bf7",
    "/chunk-7UZYWCAJ.js": "da39a3ee5e6b4b0d3255bfef95601890afd80709",
    "/chunk-ANLIW4M2.js": "244c5482b985fb0d2fc2bef0c9c408f09f113a79",
    "/chunk-AOZPS5RL.js": "9b8abfc51c939d14278476b1e93ecab35ed08857",
    "/chunk-AS3FNOMA.js": "c74ef8f408b75531094aa29d5a5003e0473ed0ac",
    "/chunk-B4CAXBEG.js": "bd3db0bd3fed9b276d281ca216736bb0d17c458a",
    "/chunk-BEFSL7UU.js": "0ccc69abe1da9f1c6cd79be4a8707d752496d3bc",
    "/chunk-BYAQRIZS.js": "c8a77a6f2eb0087fb283443be1e490674fc48aef",
    "/chunk-C7TNQJZF.js": "b5376029c0728b57e5a38ddebad45e3bf09f85b6",
    "/chunk-CI3K2WSU.js": "388e2b591bff7614d6ad7c8dfb26c250e1243da2",
    "/chunk-CKE2KE55.js": "de666c9d20abceaec50f8ae41abd0d5fc198fb2f",
    "/chunk-CQALS4LV.js": "bb3f3033d586ac0fad2747add2092af19263f839",
    "/chunk-CV62PXL2.js": "c1da154346a0264493133f9eac81cf2ecdb209fe",
    "/chunk-CVA3OUYK.js": "9a1c032d5892da75a3d80a006df29d7cafc55312",
    "/chunk-D5BJGGEH.js": "8baf27cc48201d44a860a34c8f086da9b797af26",
    "/chunk-DEKAXLAX.js": "edae4bc3e4a1fd23569fc8bcfd0009aaa6f100c3",
    "/chunk-E7AQ6X4Y.js": "a6d8bb99ff2c34d544942aaf84ae7f083792e169",
    "/chunk-E7H4FHC6.js": "86277f65cd11f0df2c4e3553b81e48e6bca326c4",
    "/chunk-EBJYW3C2.js": "ffd1d022ca2d92ec1ccbc0692e0eb7633dc471f4",
    "/chunk-EE2HNWMR.js": "8111e410d08f9830b71a79e21564271c62872820",
    "/chunk-EE3OZHXG.js": "a93c1314eb81acbf9536247d6607e632dcd8114a",
    "/chunk-EJWNUG5D.js": "c77088e3f22d9a6f23b10a4c6f197504958de8f7",
    "/chunk-EQDQRRRY.js": "c40057a332d0341d595cc1d005fc2ab4f2573957",
    "/chunk-EWYNZ3T6.js": "42c82d91a882416d0eac5c2e05837545317aa09d",
    "/chunk-FBCHPQNP.js": "8bcbc784e3ad66920c1d0f96d5ae2934f6b886c2",
    "/chunk-FJY5KO7T.js": "46c4fb877c9e0e68cf78e2e8f8a7f5c4b32b1d1a",
    "/chunk-FUINNIJL.js": "8e342a2cae1cbfecf6860718a440fd47d7ab4d19",
    "/chunk-FWCPX4QV.js": "87a76b99204bdbddee5eb223cddf8698ec1b5eb0",
    "/chunk-GOSO7CR6.js": "c1f4a179a97290fcc715385bb5cde219c251b458",
    "/chunk-GVQJJU27.js": "4fbb4537897e5889d37f84db2477161e177e3066",
    "/chunk-GWNY4E3S.js": "0bc1b19b4b482ad250c00e72324a470e45e14c8c",
    "/chunk-HFRGPHGK.js": "1092286dded59db310e39627a327a512e0a42112",
    "/chunk-HZBF5Z2J.js": "7de7f3d70735bb2d722734babfd122dd292d5441",
    "/chunk-IABRCUVS.js": "eefe1ac7cf7f92f8daa199803e99caadb2c568a2",
    "/chunk-IE4XPFBV.js": "8fbd527b509578febf0a143ad996a5442980e21c",
    "/chunk-IN5CGMY2.js": "73018b21aaba2e5409eeda138c74ed69153a9ad5",
    "/chunk-ISPOGFK5.js": "dd2042d48c0d3b80c36b8cdc9d0415b03261b04f",
    "/chunk-J6FMTRGJ.js": "f8658713b2b4905039db5a5b08e7f391c04df91e",
    "/chunk-JBX6OC6U.js": "09b41b3b27de97f8a213f3a5e7a62efa7d9676e8",
    "/chunk-JFPH4BJU.js": "e6fb56448298b80d7cbedf303ec7c46d60be075a",
    "/chunk-JO4DRFJG.js": "21da86640fa79e281b591f7c8dc03b454a9e9842",
    "/chunk-JRV6D33A.js": "7444902ad363eae0562fcb3d20319d2d5e1e7ed8",
    "/chunk-KSJ6ZHDJ.js": "be9fbdf73d7edd96d4bafdd11e118d31d06425fc",
    "/chunk-KYEGXUPT.js": "e0b0485206ca0453f718990fa6f8bbbc94a1a554",
    "/chunk-L267FACM.js": "097d921eaa4b4ef8a467bdc463fcc1e0a4c58c06",
    "/chunk-L64YGAYQ.js": "acf53992eac5f3882dc19cf8b7e265480a327d47",
    "/chunk-LMV7XNWS.js": "5ed1c4d015cff4bc383fbab02ce45f3a41bdfd2c",
    "/chunk-LXBTVQ6C.js": "0a8b4be405f376383415ffe82324f0ced00f6310",
    "/chunk-LYWS3EQM.js": "d0d0223b4226b7e1e60f79ff95e63da7732b7aec",
    "/chunk-M2VBT7VT.js": "3c9011efc1fbce9342ee63880c48cc7d3a13dce0",
    "/chunk-MXRZJWAE.js": "81164ba80fb41373c9de3a853f0cb19f7440f351",
    "/chunk-NKKODL53.js": "76cb301d3fe9b68a59d9b7316ebbdde3b570f030",
    "/chunk-NQ5JYPMZ.js": "7bed5aa0b010ff7909f0e9940a7e6defb091b1e4",
    "/chunk-OCAOS45R.js": "5d5db50597c8703d40b79ab56ca7f03dd7681646",
    "/chunk-ODKAJW66.js": "de671be4064b3a985549fb6b225395f47bc4284b",
    "/chunk-P5ZGQUYK.js": "05275202757692d3d278984902175d3462cbae45",
    "/chunk-PCDFLCFQ.js": "edfaec2af2591ab41d2391658c4de5a1a71e2efc",
    "/chunk-PXQKGGUN.js": "e19d3155d40669193f6ab53fe5544a905a0e9ed9",
    "/chunk-PY62MJCA.js": "f2c981bb9564e04fc476d13ecbf874df379d8111",
    "/chunk-Q6MIBXXU.js": "e245eff73f5264bcb0cac1db8e4e0ecb179c9b1f",
    "/chunk-QJE73BZP.js": "791530e59a475b57f9b0bd2c9d669505f89a997a",
    "/chunk-QVMFGACW.js": "6e2600b3e9928f2bc8283e5098f39be2e20882d8",
    "/chunk-R265V6BS.js": "dae951f745de4e6496cbb3659d34d3140e1a8c3e",
    "/chunk-RHXYTOW7.js": "1dadc2bb2b8ef35a0fa04ae5e0474d7c8e57b14f",
    "/chunk-SFZAX3ZK.js": "2a26d68c333db2b40fcc89949c13007e759d8378",
    "/chunk-STMJJCCP.js": "0dea45c972dc32db220be91ef55769bfd73db907",
    "/chunk-TAMGTV3V.js": "715288dfbbacd2aa9b251a78b7474d6cfe936d6c",
    "/chunk-TDSKTGHS.js": "b970e716008ad233f7516f02f3abd4a57e7bd759",
    "/chunk-TJHQUM2E.js": "1bc00c8f7aaf34d903d765f71860a0aeb6b8bf2e",
    "/chunk-TQK6WSWP.js": "631637d92dfd909b51966769de8f0c850372345a",
    "/chunk-U6EES5RG.js": "0d7047b67a0f6fd5d40e938dd9db332db4001f3c",
    "/chunk-UWEQFVWP.js": "8b37be7bfdc0ae3875bbf92198889f6af4f6387d",
    "/chunk-V54ZWV6J.js": "3452f866e461c9af30000399be6a8377f395a6d3",
    "/chunk-V6MGZ35S.js": "db07284a12861467c0dbaae1dc9dc3a23e697028",
    "/chunk-VG5Y5GOD.js": "20abf5ac82a988199882e3e0aa3294e904c8069a",
    "/chunk-WR5RRO56.js": "3c55c3bcc39184aff4349bd7b0e974f8fc458d42",
    "/chunk-WZ35W2ON.js": "8ff0558094cb24dd8a09767fe8f0a547fd64208d",
    "/chunk-X6CIBPON.js": "e4c1666f4b4aa1a5fb4ccea5d2ab07e95ad71624",
    "/chunk-XPONP6K5.js": "6f5f1c122012cecf867f78dc96182a87dd4888a8",
    "/chunk-Y6TWN2IB.js": "f9114a6c26a550b661c3d4d6be12bc0cf5f10f14",
    "/chunk-YGREV7VD.js": "811691ec1aa2d1a33100f3d5f5a9d0337776adbf",
    "/chunk-YHXWWA2F.js": "517d7d15e9dbb1bc997958837fac647b531f25b7",
    "/chunk-YSK4XEVS.js": "b2c07a4962889cd4f67db511eecd275627b59b6e",
    "/chunk-YYATEFRI.js": "ba7cea16195a0659fb10c11a19a9e661f396aec9",
    "/chunk-ZNVG5ZVS.js": "ef08f801d9a8b17266c3df98236728a2619a544c",
    "/chunk-ZQX6GPNJ.js": "5bee3cdde798ef62bd8caf5801380046cd18f2a5",
    "/chunk-ZX7FFNRS.js": "ea10fe8bb528273fdd34973739e8a853d87e79f8",
    "/index.html": "8b51c30179c12f595fcb2824a6aabddc9495061a",
    "/main-EDQZWXBM.js": "7c1f82542524a21de1b5188204f54ecd3fd07919",
    "/media/layers-2x-TBM42ERR.png": "152a162333e46d24f9d89f566312fc0c64011dee",
    "/media/layers-55W3Q4RM.png": "c9e7528e491a39232ba24a2706c6c739d6fb0f06",
    "/media/marker-icon-2V3QKKVC.png": "60a90bcbb2b42b7ddb4556db94eb7c1084b0e5da",
    "/polyfills-7UFKQPMO.js": "b017a5d37540a6ae1676379fd412a178b1dff14c",
    "/styles-M7H7SQDV.css": "bf377ae2f74fef3448eaca52c13ab13efa1a0859"
  },
  "navigationUrls": [
    {
      "positive": true,
      "regex": "^\\/.*$"
    },
    {
      "positive": false,
      "regex": "^\\/(?:.+\\/)?[^/]*\\.[^/]*$"
    },
    {
      "positive": false,
      "regex": "^\\/(?:.+\\/)?[^/]*__[^/]*$"
    },
    {
      "positive": false,
      "regex": "^\\/(?:.+\\/)?[^/]*__[^/]*\\/.*$"
    }
  ],
  "navigationRequestStrategy": "performance"
}